alarm/__init__.py
alarm/__main__.py
alarm/alarm.py
alarm/audio.py
alarm/cli.py
alarm/constants.py
alarm/exceptions.py
alarm/files.py
pybites_alarm-0.0.6.dist-info/entry_points.txt
pybites_alarm-0.0.6.dist-info/LICENSE
pybites_alarm-0.0.6.dist-info/WHEEL
pybites_alarm-0.0.6.dist-info/METADATA
pybites_alarm-0.0.6.dist-info/RECORD
