Metadata-Version: 2.1
Name: pybites-alarm
Version: 0.0.6
Summary: A package to play an alarm after an interval
Author-email: PyBites <support@pybit.es>
Requires-Python: >=3.7
Classifier: License :: OSI Approved :: MIT License
Requires-Dist: python-dotenv >=0.19.0
Requires-Dist: pydub >=0.25.1
Requires-Dist: simpleaudio >=1.0.4
Requires-Dist: audio-program-generator >=1.6.5
Project-URL: Source, https://github.com/PyBites-Open-Source/pybites-alarm
